xflsvg/__init__.py
xflsvg/recorder.py
xflsvg/renderer.py
xflsvg/xflsvg.py
xflsvg/xfl_template/DOMDocument.xml
xflsvg/xfl_template/MobileSettings.xml
xflsvg/xfl_template/PublishSettings.xml
xflsvg/xfl_template/xfl_template.xfl
xflsvg/xfl_template/LIBRARY/SymbolName.xml
xflsvg/xfl_template/META-INF/metadata.xml
xflsvg/xfl_template/bin/SymDepend.cache
xflsvg-0.1.4.dist-info/METADATA
xflsvg-0.1.4.dist-info/WHEEL
xflsvg-0.1.4.dist-info/top_level.txt
xflsvg-0.1.4.dist-info/RECORD
