Metadata-Version: 2.1
Name: xflsvg
Version: 0.1.4
Summary: A tool for working with XFL/XflSvg data.
Home-page: https://github.com/synthbot-anon/synthanim
Author: Synthbot
Author-email: synthbot.anon@gmail.com
License: Copyright 2021 Synthbot        
Platform: UNKNOWN
Classifier: Development Status :: 1 - Planning
Classifier: Intended Audience :: Science/Research
Classifier: Operating System :: POSIX :: Linux
Classifier: Operating System :: Microsoft :: Windows
Classifier: Programming Language :: Python :: 3
Classifier: Topic :: Scientific/Engineering :: Artificial Intelligence
Requires-Dist: bs4
Requires-Dist: html5lib
Requires-Dist: lxml
Requires-Dist: pandas
Requires-Dist: fastparquet
